djangoat/__init__.py
djangoat-0.0.1.dist-info/LICENSE
djangoat-0.0.1.dist-info/METADATA
djangoat-0.0.1.dist-info/WHEEL
djangoat-0.0.1.dist-info/top_level.txt
djangoat-0.0.1.dist-info/RECORD
